pyeasydriver/__init__.py
pyeasydriver/easydriver.py
pyeasydriver-0.0.1.dist-info/LICENSE
pyeasydriver-0.0.1.dist-info/METADATA
pyeasydriver-0.0.1.dist-info/WHEEL
pyeasydriver-0.0.1.dist-info/top_level.txt
pyeasydriver-0.0.1.dist-info/RECORD
