Metadata-Version: 2.1
Name: pyeasydriver
Version: 0.0.1
Summary: Driver for stepper motors controlled by SparkFun EasyDriver board
Home-page: https://github.com/ECE-492-W2020-Group-6/pyeasydriver
Author: Ishaat Chowdhury
Author-email: ishaat@ualberta.ca
License: MIT
Platform: UNKNOWN
Classifier: Programming Language :: Python :: 3
Classifier: License :: OSI Approved :: MIT License
Classifier: Operating System :: OS Independent
Requires-Python: >=3.4
Requires-Dist: gpiozero (>=1.5.1)
